owasp_logger/__init__.py
owasp_logger/logger.py
owasp_logger/model.py
owasp_logger/otel.py
owasp_logger/py.typed
owasp_logger-0.1.4.dist-info/METADATA
owasp_logger-0.1.4.dist-info/WHEEL
owasp_logger-0.1.4.dist-info/RECORD
