Metadata-Version: 2.4
Name: owasp-logger
Version: 0.1.4
Summary: OWASP-compliant structured security event logger for Python applications.
Project-URL: Homepage, https://github.com/lucabello/owasp-logger
Project-URL: Repository, https://github.com/lucabello/owasp-logger
Project-URL: Issues, https://github.com/lucabello/owasp-logger/issues
Author-email: Luca Bello <luca.bello@canonical.com>
License-Expression: Apache-2.0
Requires-Python: >=3.8
Provides-Extra: otel
Requires-Dist: opentelemetry-api; extra == 'otel'
Requires-Dist: opentelemetry-instrumentation; extra == 'otel'
Requires-Dist: opentelemetry-sdk; extra == 'otel'
